<?xml version="1.0" ?>
<!DOCTYPE PubmedArticleSet PUBLIC "-//NLM//DTD PubMedArticle, 1st January 2023//EN" "https://dtd.nlm.nih.gov/ncbi/pubmed/out/pubmed_230101.dtd">
<PubmedArticleSet>
<PubmedArticle><MedlineCitation Status="Publisher" Owner="NLM" IndexingMethod="Automated"><PMID Version="1">37797839</PMID><DateRevised><Year>2023</Year><Month>10</Month><Day>05</Day></DateRevised><Article PubModel="Print-Electronic"><Journal><ISSN IssnType="Electronic">1097-6787</ISSN><JournalIssue CitedMedium="Internet"><PubDate><Year>2023</Year><Month>Oct</Month><Day>03</Day></PubDate></JournalIssue><Title>Journal of the American Academy of Dermatology</Title><ISOAbbreviation>J Am Acad Dermatol</ISOAbbreviation></Journal><ArticleTitle>REPLY to MS#JAAD-D-23-01330R2.</ArticleTitle><ELocationID EIdType="pii" ValidYN="Y">S0190-9622(23)02887-6</ELocationID><ELocationID EIdType="doi" ValidYN="Y">10.1016/j.jaad.2023.08.107</ELocationID><AuthorList CompleteYN="Y"><Author ValidYN="Y"><LastName>Hooper</LastName><ForeName>Madeline J</ForeName><Initials>MJ</Initials><AffiliationInfo><Affiliation>Department of Dermatology, Northwestern University Feinberg School of Medicine, Chicago, IL, USA.</Affiliation></AffiliationInfo></Author><Author ValidYN="Y"><LastName>Veon</LastName><ForeName>Francesca L</ForeName><Initials>FL</Initials><AffiliationInfo><Affiliation>Department of Dermatology, Northwestern University Feinberg School of Medicine, Chicago, IL, USA.</Affiliation></AffiliationInfo></Author><Author ValidYN="Y"><LastName>Enriquez</LastName><ForeName>Gail L</ForeName><Initials>GL</Initials><AffiliationInfo><Affiliation>Department of Biology, Loyola University Chicago, Chicago, IL, USA.</Affiliation></AffiliationInfo></Author><Author ValidYN="Y"><LastName>Nguyen</LastName><ForeName>Morgan</ForeName><Initials>M</Initials><AffiliationInfo><Affiliation>Department of Dermatology, Northwestern University Feinberg School of Medicine, Chicago, IL, USA.</Affiliation></AffiliationInfo></Author><Author ValidYN="Y"><LastName>Grimes</LastName><ForeName>Cameron B</ForeName><Initials>CB</Initials><AffiliationInfo><Affiliation>Department of Dermatology, Northwestern University Feinberg School of Medicine, Chicago, IL, USA.</Affiliation></AffiliationInfo></Author><Author ValidYN="Y"><LastName>LeWitt</LastName><ForeName>Tessa M</ForeName><Initials>TM</Initials><AffiliationInfo><Affiliation>Department of Dermatology, Northwestern University Feinberg School of Medicine, Chicago, IL, USA.</Affiliation></AffiliationInfo></Author><Author ValidYN="Y"><LastName>Pang</LastName><ForeName>Yanzhen</ForeName><Initials>Y</Initials><AffiliationInfo><Affiliation>Department of Dermatology, Northwestern University Feinberg School of Medicine, Chicago, IL, USA.</Affiliation></AffiliationInfo></Author><Author ValidYN="Y"><LastName>Case</LastName><ForeName>Slaton</ForeName><Initials>S</Initials><AffiliationInfo><Affiliation>Department of Dermatology, Northwestern University Feinberg School of Medicine, Chicago, IL, USA.</Affiliation></AffiliationInfo></Author><Author ValidYN="Y"><LastName>Choi</LastName><ForeName>Jaehyuk</ForeName><Initials>J</Initials><AffiliationInfo><Affiliation>Department of Dermatology, Northwestern University Feinberg School of Medicine, Chicago, IL, USA.</Affiliation></AffiliationInfo></Author><Author ValidYN="Y"><LastName>Guitart</LastName><ForeName>Joan</ForeName><Initials>J</Initials><AffiliationInfo><Affiliation>Department of Dermatology, Northwestern University Feinberg School of Medicine, Chicago, IL, USA.</Affiliation></AffiliationInfo></Author><Author ValidYN="Y"><LastName>Burns</LastName><ForeName>Michael B</ForeName><Initials>MB</Initials><AffiliationInfo><Affiliation>Department of Biology, Loyola University Chicago, Chicago, IL, USA.</Affiliation></AffiliationInfo></Author><Author ValidYN="Y"><LastName>Zhou</LastName><ForeName>Xiaolong A</ForeName><Initials>XA</Initials><AffiliationInfo><Affiliation>Department of Dermatology, Northwestern University Feinberg School of Medicine, Chicago, IL, USA. Electronic address: alan.zhou@northwestern.edu.</Affiliation></AffiliationInfo></Author></AuthorList><Language>eng</Language><PublicationTypeList><PublicationType UI="D016422">Letter</PublicationType></PublicationTypeList><ArticleDate DateType="Electronic"><Year>2023</Year><Month>10</Month><Day>03</Day></ArticleDate></Article><MedlineJournalInfo><Country>United States</Country><MedlineTA>J Am Acad Dermatol</MedlineTA><NlmUniqueID>7907132</NlmUniqueID><ISSNLinking>0190-9622</ISSNLinking></MedlineJournalInfo><CitationSubset>IM</CitationSubset><KeywordList Owner="NOTNLM"><Keyword MajorTopicYN="N">Black patients</Keyword><Keyword MajorTopicYN="N">bacteremia</Keyword><Keyword MajorTopicYN="N">cutaneous T-cell lymphoma</Keyword><Keyword MajorTopicYN="N">non-Hodgkin lymphoma</Keyword><Keyword MajorTopicYN="N">outcomes</Keyword><Keyword MajorTopicYN="N">race</Keyword><Keyword MajorTopicYN="N">risk factors</Keyword><Keyword MajorTopicYN="N">sepsis</Keyword></KeywordList></MedlineCitation><PubmedData><History><PubMedPubDate PubStatus="received"><Year>2023</Year><Month>8</Month><Day>26</Day></PubMedPubDate><PubMedPubDate PubStatus="accepted"><Year>2023</Year><Month>8</Month><Day>28</Day></PubMedPubDate><PubMedPubDate PubStatus="medline"><Year>2023</Year><Month>10</Month><Day>6</Day><Hour>0</Hour><Minute>43</Minute></PubMedPubDate><PubMedPubDate PubStatus="pubmed"><Year>2023</Year><Month>10</Month><Day>6</Day><Hour>0</Hour><Minute>43</Minute></PubMedPubDate><PubMedPubDate PubStatus="entrez"><Year>2023</Year><Month>10</Month><Day>5</Day><Hour>19</Hour><Minute>33</Minute></PubMedPubDate></History><PublicationStatus>aheadofprint</PublicationStatus><ArticleIdList><ArticleId IdType="pubmed">37797839</ArticleId><ArticleId IdType="doi">10.1016/j.jaad.2023.08.107</ArticleId><ArticleId IdType="pii">S0190-9622(23)02887-6</ArticleId></ArticleIdList></PubmedData></PubmedArticle></PubmedArticleSet>